<?xml version="1.0" encoding="UTF-8" ?>
<!DOCTYPE mapper PUBLIC "-//mybatis.org//DTD Mapper 3.0//EN" "http://mybatis.org/dtd/mybatis-3-mapper.dtd" >
<mapper namespace="com.example.tenet.dao.NoteDao" >
    <resultMap id="NoteRow" type="com.example.tenet.entity.NoteEntity">
        <result column="note_id" property="note_id" />
        <result column="test" property="test" />
        <result column="tittle" property="tittle" />
        <result column="label" property="label" />
    </resultMap>
    <resultMap id="note_id" type="integer" />
    <insert id="insert" useGeneratedKeys="true" keyProperty="noteEntity.note_id" keyColumn="note_id">
    insert into note
      (test,tittle,label) VALUES
      (#{noteEntity.test},#{noteEntity.tittle},#{noteEntity.label})
  </insert>
</mapper>